ytdvideo.py
ytdvideo-2.0.0.dist-info/LICENSE
ytdvideo-2.0.0.dist-info/METADATA
ytdvideo-2.0.0.dist-info/WHEEL
ytdvideo-2.0.0.dist-info/top_level.txt
ytdvideo-2.0.0.dist-info/RECORD
