Metadata-Version: 2.1
Name: ytdvideo
Version: 2.0.0
Summary: A Python package to get Youtube Videos from any channel can save the data as JSON and EXCEL 
Home-page: https://github.com/soumilshah1995/YoutubeVideo
Author: Soumil Nitin Shah
Author-email: soushah@my.bridgeport.edu
License: MIT
Platform: UNKNOWN
Classifier: License :: OSI Approved :: MIT License
Classifier: Programming Language :: Python :: 3
Classifier: Programming Language :: Python :: 3.7
Requires-Dist: pandas (==0.24.0)
Requires-Dist: google-api-python-client (==1.7.8)
